snuffkin_playground/__init__.py
snuffkin_playground/sample.py
snuffkin_playground-0.1.1.dist-info/LICENSE
snuffkin_playground-0.1.1.dist-info/METADATA
snuffkin_playground-0.1.1.dist-info/WHEEL
snuffkin_playground-0.1.1.dist-info/top_level.txt
snuffkin_playground-0.1.1.dist-info/RECORD
